aws_ci_cd_lambda/__init__.py
aws_ci_cd_lambda/buildspec_object.py
aws_ci_cd_lambda/ci_cd_lambda.py
aws_ci_cd_lambda/lambda_alarms.py
aws_ci_cd_lambda/custom/__init__.py
aws_ci_cd_lambda/custom/initial_commit.py
aws_ci_cd_lambda/files/__init__.py
aws_ci_cd_lambda/files/install.sh
aws_ci_cd_lambda/files/manage.py
aws_ci_cd_lambda/files/test.sh
aws_ci_cd_lambda/parameters/__init__.py
aws_ci_cd_lambda/parameters/lambda_parameters.py
aws_ci_cd_lambda/parameters/pipeline_parameters.py
aws_ci_cd_lambda/parameters/ssh_parameters.py
aws_ci_cd_lambda/parameters/vpc_parameters.py
aws_ci_cd_lambda-3.4.0.dist-info/LICENSE
aws_ci_cd_lambda-3.4.0.dist-info/METADATA
aws_ci_cd_lambda-3.4.0.dist-info/WHEEL
aws_ci_cd_lambda-3.4.0.dist-info/top_level.txt
aws_ci_cd_lambda-3.4.0.dist-info/RECORD
