Metadata-Version: 2.1
Name: aws-ci-cd-lambda
Version: 3.4.0
Summary: AWS CDK package that helps deploying a lambda function.
Home-page: https://github.com/idenfy/AwsCiCdLambda.git
Author: Deividas Tamkus
Author-email: dtamkus@gmail.com
License: GNU GENERAL PUBLIC LICENSE Version 3
Keywords: AWS CDK Ci/Cd Lambda Pipeline
Platform: UNKNOWN
Classifier: Programming Language :: Python :: 3
Classifier: Operating System :: OS Independent
Requires-Dist: aws-cdk.core (<2.0.0,>=1.60.0)
Requires-Dist: aws-cdk.aws-iam (<2.0.0,>=1.60.0)
Requires-Dist: aws-cdk.custom-resources (<2.0.0,>=1.60.0)
Requires-Dist: aws-cdk.aws-lambda (<2.0.0,>=1.60.0)
Requires-Dist: aws-cdk.aws-codecommit (<2.0.0,>=1.60.0)
Requires-Dist: aws-cdk.aws-codebuild (<2.0.0,>=1.60.0)
Requires-Dist: aws-cdk.aws-codepipeline (<2.0.0,>=1.60.0)
Requires-Dist: aws-cdk.aws-codepipeline-actions (<2.0.0,>=1.60.0)
Requires-Dist: aws-cdk.aws-ec2 (<2.0.0,>=1.60.0)
Requires-Dist: aws-empty-bucket (<3.0.0,>=2.0.0)
